LICENSE
MANIFEST.in
README.md
requirements.txt
setup.py
sinfonier_api/__init__.py
sinfonier_api/config.py
sinfonier_api/modulehandler.py
sinfonier_api/mongohandler.py
sinfonier_api/sinfonierapicore.py
sinfonier_api/statushandler.py
sinfonier_api/stormloghandler.py
sinfonier_api/stormuiapi.py
sinfonier_api/topologyhandler.py
sinfonier_api/utils.py
sinfonier_api.egg-info/PKG-INFO
sinfonier_api.egg-info/SOURCES.txt
sinfonier_api.egg-info/dependency_links.txt
sinfonier_api.egg-info/entry_points.txt
sinfonier_api.egg-info/requires.txt
sinfonier_api.egg-info/top_level.txt