Metadata-Version: 1.1
Name: sinfonier-api
Version: 1.0.0
Summary: Sinfonier API was develop to manage Sinfonier Backend and deal with Apache Storm cluster. This software is part of Sinfonier-Project
Home-page: https://github.com/sinfonier-project/sinfonier-api
Author: Sinfonier Project
Author-email: UNKNOWN
License: Apache License
Platform: UNKNOWN
Classifier: Environment :: Console
Classifier: Intended Audience :: System Administrators
Classifier: Intended Audience :: Other Audience
Classifier: License :: OSI Approved :: BSD License
Classifier: Operating System :: MacOS
Classifier: Operating System :: Microsoft :: Windows
Classifier: Operating System :: POSIX
Classifier: Programming Language :: Python :: 2
Classifier: Programming Language :: Python :: 3
Classifier: Topic :: Security
